hardware_tools/version.py
hardware_tools/strformat.py
hardware_tools/__init__.py
hardware_tools/math/_lines.cpython-38-x86_64-linux-gnu.so
hardware_tools/math/image.py
hardware_tools/math/lines.py
hardware_tools/math/stats.py
hardware_tools/math/interpolation.py
hardware_tools/math/gaussian.py
hardware_tools/math/_lines.pxd
hardware_tools/math/_lines_fb.py
hardware_tools/math/__init__.py
hardware_tools/measurement/mask.py
hardware_tools/measurement/__init__.py
hardware_tools/measurement/eyediagram/_eyediagram.pxd
hardware_tools/measurement/eyediagram/_eyediagram.cpython-38-x86_64-linux-gnu.so
hardware_tools/measurement/eyediagram/pam2.py
hardware_tools/measurement/eyediagram/_pam2_fb.py
hardware_tools/measurement/eyediagram/_eyediagram_fb.py
hardware_tools/measurement/eyediagram/_pam2.pxd
hardware_tools/measurement/eyediagram/_cdr_fb.py
hardware_tools/measurement/eyediagram/_cdr.cpython-38-x86_64-linux-gnu.so
hardware_tools/measurement/eyediagram/_cdr.pxd
hardware_tools/measurement/eyediagram/eyediagram.py
hardware_tools/measurement/eyediagram/__init__.py
hardware_tools/measurement/eyediagram/_pam2.cpython-38-x86_64-linux-gnu.so
hardware_tools/measurement/eyediagram/cdr.py
hardware_tools/signal/clock.py
hardware_tools/signal/__init__.py
hardware_tools/equipment/scope.py
hardware_tools/equipment/equipment.py
hardware_tools/equipment/__init__.py
hardware_tools/equipment/utility.py
hardware_tools/equipment/tektronix/common.py
hardware_tools/equipment/tektronix/family_mso4000.py
hardware_tools/equipment/tektronix/family_mso456.py
hardware_tools/equipment/tektronix/__init__.py
hardware_tools-0.10.0.dist-info/WHEEL
hardware_tools-0.10.0.dist-info/top_level.txt
hardware_tools-0.10.0.dist-info/LICENSE
hardware_tools-0.10.0.dist-info/RECORD
hardware_tools-0.10.0.dist-info/METADATA
