Metadata-Version: 2.1
Name: hardware-tools
Version: 0.10.0
Summary: A library for automating hardware development and testing
Home-page: https://github.com/WattsUp/hardware-tools
Author: Bradley Davis
Author-email: me@bradleydavis.tech
License: MIT
Classifier: Programming Language :: Python :: 3
Classifier: Operating System :: OS Independent
Classifier: Development Status :: 2 - Pre-Alpha
Classifier: License :: OSI Approved :: MIT License
Classifier: Intended Audience :: Developers
Classifier: Topic :: Scientific/Engineering :: Electronic Design Automation (EDA)
Classifier: Topic :: Scientific/Engineering :: Information Analysis
Classifier: Topic :: Scientific/Engineering :: Visualization
Classifier: Programming Language :: Python :: 3.7
Classifier: Programming Language :: Python :: 3.8
Classifier: Programming Language :: Python :: 3.9
Classifier: Programming Language :: Python :: 3.10
Requires-Python: >=3.7
License-File: LICENSE
Requires-Dist: numpy
Requires-Dist: pyvisa
Requires-Dist: colorama
Requires-Dist: matplotlib
Requires-Dist: scipy
Requires-Dist: scikit-learn
Requires-Dist: Pillow
Requires-Dist: scikit-image
Provides-Extra: test
Requires-Dist: time-machine ; extra == 'test'
Requires-Dist: AutoDict ; extra == 'test'
Requires-Dist: coverage ; extra == 'test'
Requires-Dist: pylint ; extra == 'test'
Requires-Dist: witch-ver ; extra == 'test'
